vope/__init__.py
vope/myfunctions.py
vope-0.1.0.dist-info/METADATA
vope-0.1.0.dist-info/WHEEL
vope-0.1.0.dist-info/top_level.txt
vope-0.1.0.dist-info/RECORD
