Metadata-Version: 2.1
Name: vope
Version: 0.1.0
Summary: Improving laparoscopy image visualization.
Home-page: UNKNOWN
Author: Sharif Natheir
Author-email: UNKNOWN
License: MIT
Platform: UNKNOWN
